namaste_samsara/__init__.py
namaste_samsara/main.py
namaste_samsara-0.3.dist-info/METADATA
namaste_samsara-0.3.dist-info/WHEEL
namaste_samsara-0.3.dist-info/entry_points.txt
namaste_samsara-0.3.dist-info/top_level.txt
namaste_samsara-0.3.dist-info/RECORD
