Metadata-Version: 2.1
Name: namaste_samsara
Version: 0.3
